pyneospider/__init__.py
pyneospider/pyneospider.py
pyneospider-0.0.5.dist-info/LICENSE
pyneospider-0.0.5.dist-info/METADATA
pyneospider-0.0.5.dist-info/WHEEL
pyneospider-0.0.5.dist-info/top_level.txt
pyneospider-0.0.5.dist-info/RECORD
