Metadata-Version: 2.1
Name: pyneospider
Version: 0.0.5
Summary: python NeoSpider library
Home-page: https://github.com/Neo3ds/pyneospider.git
Author: TaeJuneJoung
Author-email: jtj0525@gmail.com
License: MIT
Classifier: Programming Language :: Python :: 3
Classifier: License :: OSI Approved :: MIT License
Classifier: Operating System :: OS Independent
Requires-Python: >=3.6
License-File: LICENSE
Requires-Dist: pyserial
